{
  "args: (0, 0, 8)": "result: такого не может быть---------------------------------------------------",
  "args: (0, -6, 4)": "result: x=0.6666666666666666",
  "args: (1, 7, -10)": "result: d = 89 x1 = -8.2169905660283 x2 = 1.2169905660283016",
  "args: (8, -6, 5)": "result: d = -124 нет действительных корней",
  "args: (-5, 0, 9)": "result: d = 180 x1 = 33.54101966249685 x2 = -33.54101966249685",
  "args: (0, -4, 8)": "result: x=2.0",
  "args: (-10, 7, 8)": "result: d = 369 x1 = 131.04686356149273 x2 = -61.04686356149273",
  "args: (4, 3, -4)": "result: d = 73 x1 = -23.08800749063506 x2 = 11.08800749063506",
  "args: (-4, 4, 6)": "result: d = 112 x1 = 29.166010488516726 x2 = -13.166010488516726",
  "args: (-2, -5, -9)": "result: d = -47 нет действительных корней",
  "args: (6, 4, -10)": "result: d = 256 x1 = -60.0 x2 = 36.0",
  "args: (9, 5, -10)": "result: d = 385 x1 = -110.79637591656862 x2 = 65.79637591656862",
  "args: (-9, 6, -1)": "result: d = 0 x1 = x2 = 27.0",
  "args: (-9, 3, -7)": "result: d = -243 нет действительных корней",
  "args: (10, 7, -4)": "result: d = 209 x1 = -107.2841614740048 x2 = 37.284161474004804",
  "args: (-4, 2, 2)": "result: d = 36 x1 = 16.0 x2 = -8.0",
  "args: (0, 10, 8)": "result: x=-0.8",
  "args: (2, 7, 0)": "result: d = 49 x1 = -14.0 x2 = -0.0",
  "args: (10, 1, -2)": "result: d = 81 x1 = -50.0 x2 = 40.0",
  "args: (-1, -2, 10)": "result: d = 44 x1 = 2.3166247903554 x2 = -4.3166247903554",
  "args: (-9, -3, 5)": "result: d = 189 x1 = 48.36477188190384 x2 = -75.36477188190383",
  "args: (3, 5, -4)": "result: d = 73 x1 = -20.316005617976295 x2 = 5.316005617976296",
  "args: (-7, -7, -6)": "result: d = -119 нет действительных корней",
  "args: (-8, 10, 2)": "result: d = 164 x1 = 91.22499389946279 x2 = -11.224993899462788",
  "args: (-3, -8, -5)": "result: d = 4 x1 = -9.0 x2 = -15.0",
  "args: (-2, 1, -1)": "result: d = -7 нет действительных корней",
  "args: (7, 0, 8)": "result: d = -224 нет действительных корней",
  "args: (1, -4, 9)": "result: d = -20 нет действительных корней",
  "args: (0, -1, 10)": "result: x=10.0",
  "args: (8, -1, -4)": "result: d = 129 x1 = -41.43126676640219 x2 = 49.43126676640219",
  "args: (10, -8, -6)": "result: d = 304 x1 = -47.177978870813476 x2 = 127.17797887081348",
  "args: (10, -9, -1)": "result: d = 121 x1 = -10.0 x2 = 100.0",
  "args: (9, 7, 7)": "result: d = -203 нет действительных корней",
  "args: (-5, 3, 10)": "result: d = 209 x1 = 43.6420807370024 x2 = -28.642080737002402",
  "args: (-9, -2, -4)": "result: d = -140 нет действительных корней",
  "args: (-10, 8, 4)": "result: d = 224 x1 = 114.83314773547882 x2 = -34.833147735478825",
  "args: (3, -1, -10)": "result: d = 121 x1 = -15.0 x2 = 18.0",
  "args: (-1, 0, -8)": "result: d = -32 нет действительных корней",
  "args: (-7, -9, 0)": "result: d = 81 x1 = 0.0 x2 = -63.0",
  "args: (-7, -2, 1)": "result: d = 32 x1 = 12.798989873223332 x2 = -26.79898987322333",
  "args: (0, -1, -10)": "result: x=-10.0",
  "args: (-6, -10, 7)": "result: d = 268 x1 = 19.112116631234702 x2 = -79.1121166312347",
  "args: (-7, 6, 3)": "result: d = 120 x1 = 59.340579025361635 x2 = -17.340579025361627",
  "args: (5, -7, -3)": "result: d = 109 x1 = -8.600766272276378 x2 = 43.60076627227638",
  "args: (7, -9, 1)": "result: d = 53 x1 = 6.019615387518186 x2 = 56.980384612481814",
  "args: (3, -10, -8)": "result: d = 196 x1 = -6.0 x2 = 36.0",
  "args: (-6, -10, 1)": "result: d = 124 x1 = 3.406586176980129 x2 = -63.406586176980134",
  "args: (-9, 3, 4)": "result: d = 153 x1 = 69.16192594583842 x2 = -42.16192594583841",
  "args: (-9, 1, 5)": "result: d = 181 x1 = 65.04130821183169 x2 = -56.04130821183169",
  "args: (7, -2, -2)": "result: d = 60 x1 = -20.11088342345192 x2 = 34.11088342345192",
  "args: (-8, 4, 6)": "result: d = 208 x1 = 73.68882040742383 x2 = -41.688820407423826",
  "args: (5, 9, -7)": "result: d = 221 x1 = -59.66517186829627 x2 = 14.665171868296266",
  "args: (-4, 8, -1)": "result: d = 48 x1 = 29.856406460551018 x2 = 2.1435935394489825",
  "args: (8, -5, -6)": "result: d = 217 x1 = -38.92367945062494 x2 = 78.92367945062495",
  "args: (2, 2, -4)": "result: d = 36 x1 = -8.0 x2 = 4.0",
  "args: (0, 10, -3)": "result: x=0.3",
  "args: (-6, -4, -5)": "result: d = -104 нет действительных корней",
  "args: (4, -10, 1)": "result: d = 84 x1 = 1.6696972201766407 x2 = 38.330302779823356",
  "args: (4, -4, 8)": "result: d = -112 нет действительных корней",
  "args: (8, 6, -9)": "result: d = 324 x1 = -96.0 x2 = 48.0",
  "args: (3, 1, -9)": "result: d = 109 x1 = -17.160459763365825 x2 = 14.160459763365825",
  "args: (-3, 9, 10)": "result: d = 201 x1 = 34.766170318136744 x2 = -7.766170318136738",
  "args: (-10, 5, 2)": "result: d = 105 x1 = 76.234753829798 x2 = -26.234753829797988",
  "args: (-9, 3, -9)": "result: d = -315 нет действительных корней",
  "args: (5, -4, -2)": "result: d = 56 x1 = -8.708286933869706 x2 = 28.708286933869704",
  "args: (8, -10, 3)": "result: d = 4 x1 = 32.0 x2 = 48.0",
  "args: (-8, 9, -3)": "result: d = -15 нет действительных корней",
  "args: (-1, -2, 2)": "result: d = 12 x1 = 0.7320508075688772 x2 = -2.732050807568877",
  "args: (7, 4, 10)": "result: d = -264 нет действительных корней",
  "args: (-2, 5, -6)": "result: d = -23 нет действительных корней",
  "args: (4, -8, 2)": "result: d = 32 x1 = 4.686291501015239 x2 = 27.31370849898476",
  "args: (-5, -9, -1)": "result: d = 61 x1 = -2.974375810233365 x2 = -42.02562418976663",
  "args: (-2, 7, -4)": "result: d = 17 x1 = 11.123105625617661 x2 = 2.8768943743823394",
  "args: (-4, -6, 6)": "result: d = 132 x1 = 10.978250586152114 x2 = -34.978250586152114",
  "args: (10, 8, 8)": "result: d = -256 нет действительных корней",
  "args: (-7, 6, -2)": "result: d = -20 нет действительных корней",
  "args: (-2, 5, 6)": "result: d = 73 x1 = 13.54400374531753 x2 = -3.5440037453175304",
  "args: (-1, -7, -3)": "result: d = 37 x1 = -0.45861873485089033 x2 = -6.541381265149109",
  "args: (-1, -9, -8)": "result: d = 49 x1 = -1.0 x2 = -8.0",
  "args: (4, 9, -1)": "result: d = 97 x1 = -37.69771560359221 x2 = 1.6977156035922079",
  "args: (5, 2, 10)": "result: d = -196 нет действительных корней",
  "args: (-1, -4, 9)": "result: d = 52 x1 = 1.6055512754639891 x2 = -5.60555127546399",
  "args: (-7, 8, -8)": "result: d = -160 нет действительных корней",
  "args: (-3, 7, -6)": "result: d = -23 нет действительных корней",
  "args: (-5, 7, 5)": "result: d = 149 x1 = 48.01638903933426 x2 = -13.016389039334255",
  "args: (-4, -5, 1)": "result: d = 41 x1 = 2.806248474865697 x2 = -22.806248474865697",
  "args: (-5, -4, -3)": "result: d = -44 нет действительных корней",
  "args: (-6, 6, 7)": "result: d = 204 x1 = 60.8485705712571 x2 = -24.848570571257103",
  "args: (-8, 0, 9)": "result: d = 288 x1 = 67.88225099390856 x2 = -67.88225099390856",
  "args: (9, -8, -1)": "result: d = 100 x1 = -9.0 x2 = 81.0",
  "args: (-6, -5, 6)": "result: d = 169 x1 = 24.0 x2 = -54.0",
  "args: (3, 8, -4)": "result: d = 112 x1 = -27.874507866387546 x2 = 3.8745078663875443",
  "args: (-4, 4, -3)": "result: d = -32 нет действительных корней",
  "args: (0, 9, -10)": "result: x=1.1111111111111112",
  "args: (10, 4, -7)": "result: d = 296 x1 = -106.02325267042627 x2 = 66.02325267042627",
  "args: (3, 9, -5)": "result: d = 141 x1 = -31.311513130556875 x2 = 4.311513130556875",
  "args: (3, -1, 8)": "result: d = -95 нет действительных корней",
  "args: (0, 9, 2)": "result: x=-0.2222222222222222",
  "args: (9, 10, 3)": "result: d = -8 нет действительных корней",
  "args: (9, 6, -3)": "result: d = 144 x1 = -81.0 x2 = 27.0",
  "args: (7, -5, 2)": "result: d = -31 нет действительных корней",
  "args: (2, 6, 7)": "result: d = -20 нет действительных корней",
  "args: (5, 6, -8)": "result: d = 196 x1 = -50.0 x2 = 20.0",
  "args: (7, 5, 2)": "result: d = -31 нет действительных корней",
  "args: (7, 3, 9)": "result: d = -243 нет действительных корней",
  "args: (8, -8, -7)": "result: d = 288 x1 = -35.882250993908556 x2 = 99.88225099390856",
  "args: (0, -8, 8)": "result: x=1.0",
  "args: (8, -3, 2)": "result: d = -55 нет действительных корней",
  "args: (4, 9, -8)": "result: d = 209 x1 = -46.91366458960192 x2 = 10.913664589601922",
  "args: (4, 7, 5)": "result: d = -31 нет действительных корней",
  "args: (4, -6, 8)": "result: d = -92 нет действительных корней",
  "args: (5, 2, 8)": "result: d = -156 нет действительных корней",
  "args: (10, 3, 7)": "result: d = -271 нет действительных корней",
  "args: (-2, 8, -2)": "result: d = 48 x1 = 14.928203230275509 x2 = 1.0717967697244912",
  "args: (10, -1, -1)": "result: d = 41 x1 = -27.015621187164243 x2 = 37.01562118716424",
  "args: (-1, 2, -10)": "result: d = -36 нет действительных корней",
  "args: (-1, -4, -10)": "result: d = -24 нет действительных корней",
  "args: (9, 5, 7)": "result: d = -227 нет действительных корней",
  "args: (-2, -7, -4)": "result: d = 17 x1 = -2.8768943743823394 x2 = -11.123105625617661",
  "args: (7, -3, 6)": "result: d = -159 нет действительных корней",
  "args: (3, -1, -3)": "result: d = 37 x1 = -7.6241437954473295 x2 = 10.62414379544733",
  "args: (-9, 0, -8)": "result: d = -288 нет действительных корней",
  "args: (-2, -8, 8)": "result: d = 128 x1 = 3.313708498984761 x2 = -19.31370849898476",
  "args: (-6, 3, 4)": "result: d = 105 x1 = 39.740852297878796 x2 = -21.740852297878796",
  "args: (8, 8, 8)": "result: d = -192 нет действительных корней",
  "args: (-10, 4, -5)": "result: d = -184 нет действительных корней",
  "args: (-9, -9, -2)": "result: d = 9 x1 = -27.0 x2 = -54.0",
  "args: (-4, -1, 1)": "result: d = 17 x1 = 6.246211251235321 x2 = -10.246211251235321",
  "args: (8, -8, 2)": "result: d = 0 x1 = x2 = 32.0",
  "args: (5, 7, 1)": "result: d = 29 x1 = -30.96291201783626 x2 = -4.03708798216374",
  "args: (-1, -2, -7)": "result: d = -24 нет действительных корней",
  "args: (5, 5, 10)": "result: d = -175 нет действительных корней",
  "args: (-9, -4, -4)": "result: d = -128 нет действительных корней",
  "args: (10, -1, 9)": "result: d = -359 нет действительных корней",
  "args: (4, 3, 10)": "result: d = -151 нет действительных корней",
  "args: (10, -10, -9)": "result: d = 460 x1 = -57.23805294763608 x2 = 157.23805294763608",
  "args: (8, -10, -3)": "result: d = 196 x1 = -16.0 x2 = 96.0",
  "args: (-9, 1, -4)": "result: d = -143 нет действительных корней",
  "args: (-9, 4, -4)": "result: d = -128 нет действительных корней",
  "args: (-1, 2, -6)": "result: d = -20 нет действительных корней",
  "args: (-7, 6, 0)": "result: d = 36 x1 = 42.0 x2 = 0.0",
  "args: (-7, 5, -6)": "result: d = -143 нет действительных корней",
  "args: (5, 8, 4)": "result: d = -16 нет действительных корней",
  "args: (10, -3, -7)": "result: d = 289 x1 = -70.0 x2 = 100.0",
  "args: (-3, 9, 9)": "result: d = 189 x1 = 34.12159062730128 x2 = -7.121590627301281",
  "args: (-6, 7, 6)": "result: d = 193 x1 = 62.67733196834941 x2 = -20.677331968349414",
  "args: (-6, -9, -9)": "result: d = -135 нет действительных корней",
  "args: (6, 6, 3)": "result: d = -36 нет действительных корней",
  "args: (9, 9, -6)": "result: d = 297 x1 = -118.05159572826338 x2 = 37.051595728263386",
  "args: (6, 9, -6)": "result: d = 225 x1 = -72.0 x2 = 18.0",
  "args: (3, 10, -2)": "result: d = 124 x1 = -31.703293088490067 x2 = 1.7032930884900646",
  "args: (3, -10, -6)": "result: d = 172 x1 = -4.672315572906001 x2 = 34.672315572906",
  "args: (7, -6, 0)": "result: d = 36 x1 = -0.0 x2 = 42.0",
  "args: (-10, -8, 2)": "result: d = 144 x1 = 20.0 x2 = -100.0",
  "args: (-3, 5, 6)": "result: d = 97 x1 = 22.273286702694158 x2 = -7.273286702694156",
  "args: (6, -10, -3)": "result: d = 172 x1 = -9.344631145812002 x2 = 69.344631145812",
  "args: (-2, 5, 10)": "result: d = 105 x1 = 15.246950765959598 x2 = -5.246950765959598",
  "args: (1, 8, 10)": "result: d = 24 x1 = -6.449489742783178 x2 = -1.5505102572168221",
  "args: (0, 7, -2)": "result: x=0.2857142857142857",
  "args: (-8, -1, 10)": "result: d = 321 x1 = 67.66589146867567 x2 = -75.66589146867567",
  "args: (5, 2, 0)": "result: d = 4 x1 = -10.0 x2 = -0.0",
  "args: (4, 2, -2)": "result: d = 36 x1 = -16.0 x2 = 8.0",
  "args: (-4, -3, -10)": "result: d = -151 нет действительных корней",
  "args: (9, -1, 10)": "result: d = -359 нет действительных корней",
  "args: (-3, -5, 9)": "result: d = 133 x1 = 9.798843892006195 x2 = -24.798843892006197",
  "args: (6, 1, 9)": "result: d = -215 нет действительных корней",
  "args: (-3, -4, -4)": "result: d = -32 нет действительных корней",
  "args: (-10, -4, -8)": "result: d = -304 нет действительных корней",
  "args: (-2, 6, 4)": "result: d = 68 x1 = 14.246211251235321 x2 = -2.246211251235321",
  "args: (-4, -2, 2)": "result: d = 36 x1 = 8.0 x2 = -16.0",
  "args: (10, -10, -10)": "result: d = 500 x1 = -61.80339887498949 x2 = 161.80339887498948",
  "args: (-7, -6, -5)": "result: d = -104 нет действительных корней",
  "args: (-1, 0, 6)": "result: d = 24 x1 = 2.449489742783178 x2 = -2.449489742783178",
  "args: (2, 9, 1)": "result: d = 73 x1 = -17.544003745317532 x2 = -0.4559962546824696",
  "args: (-2, 0, 1)": "result: d = 8 x1 = 2.8284271247461903 x2 = -2.8284271247461903",
  "args: (-1, -1, -3)": "result: d = -11 нет действительных корней",
  "args: (-4, -7, -5)": "result: d = -31 нет действительных корней",
  "args: (7, 6, -1)": "result: d = 64 x1 = -49.0 x2 = 7.0",
  "args: (1, 1, 0)": "result: d = 1 x1 = -1.0 x2 = -0.0",
  "args: (4, 8, -9)": "result: d = 208 x1 = -44.84441020371192 x2 = 12.844410203711913",
  "args: (8, -4, -9)": "result: d = 304 x1 = -53.742383096650784 x2 = 85.74238309665078",
  "args: (2, 8, -10)": "result: d = 144 x1 = -20.0 x2 = 4.0",
  "args: (-5, -9, -5)": "result: d = -19 нет действительных корней",
  "args: (-3, -6, 3)": "result: d = 72 x1 = 3.7279220613578543 x2 = -21.727922061357855",
  "args: (-2, -2, 9)": "result: d = 76 x1 = 6.717797887081348 x2 = -10.717797887081348",
  "args: (-7, -4, -1)": "result: d = -12 нет действительных корней",
  "args: (0, -3, 6)": "result: x=2.0",
  "args: (-10, 8, 9)": "result: d = 424 x1 = 142.95630140987 x2 = -62.95630140987001",
  "args: (-4, -3, -2)": "result: d = -23 нет действительных корней",
  "args: (-3, 10, 0)": "result: d = 100 x1 = 30.0 x2 = 0.0",
  "args: (2, 10, -9)": "result: d = 172 x1 = -23.114877048604 x2 = 3.1148770486040007",
  "args: (-9, 4, -2)": "result: d = -56 нет действительных корней",
  "args: (-4, -4, -9)": "result: d = -128 нет действительных корней",
  "args: (4, -9, -9)": "result: d = 225 x1 = -12.0 x2 = 48.0",
  "args: (7, 1, 4)": "result: d = -111 нет действительных корней",
  "args: (-3, -3, 10)": "result: d = 129 x1 = 12.53672503740082 x2 = -21.53672503740082",
  "args: (2, -5, 6)": "result: d = -23 нет действительных корней",
  "args: (-10, 7, -9)": "result: d = -311 нет действительных корней",
  "args: (-10, -3, -8)": "result: d = -311 нет действительных корней",
  "args: (9, -9, -5)": "result: d = 261 x1 = -32.1997248963158 x2 = 113.1997248963158",
  "args: (-7, 4, 1)": "result: d = 44 x1 = 37.2163735324878 x2 = -9.216373532487799",
  "args: (-7, -6, -2)": "result: d = -20 нет действительных корней",
  "args: (3, 10, -1)": "result: d = 112 x1 = -30.874507866387546 x2 = 0.8745078663875443",
  "args: (9, -5, 3)": "result: d = -83 нет действительных корней",
  "args: (0, 6, -7)": "result: x=1.1666666666666667",
  "args: (-8, -5, 3)": "result: d = 121 x1 = 24.0 x2 = -64.0",
  "args: (-2, 9, 7)": "result: d = 137 x1 = 20.704699910719626 x2 = -2.7046999107196257",
  "args: (3, -6, 7)": "result: d = -48 нет действительных корней",
  "args: (-2, -5, -5)": "result: d = -15 нет действительных корней",
  "args: (8, 5, 9)": "result: d = -263 нет действительных корней",
  "args: (-1, 3, -9)": "result: d = -27 нет действительных корней",
  "args: (-5, 3, 0)": "result: d = 9 x1 = 15.0 x2 = 0.0",
  "args: (7, 7, -2)": "result: d = 105 x1 = -60.36432768085859 x2 = 11.364327680858594",
  "args: (10, 3, -9)": "result: d = 369 x1 = -111.04686356149273 x2 = 81.04686356149273",
  "args: (-7, -9, -10)": "result: d = -199 нет действительных корней",
  "args: (-1, -10, -1)": "result: d = 96 x1 = -0.10102051443364424 x2 = -9.898979485566356",
  "args: (-2, -6, 3)": "result: d = 60 x1 = 1.745966692414834 x2 = -13.745966692414834",
  "args: (-8, -8, 9)": "result: d = 352 x1 = 43.046652157174876 x2 = -107.04665215717488",
  "args: (-8, -2, -6)": "result: d = -188 нет действительных корней",
  "args: (-10, -10, 10)": "result: d = 500 x1 = 61.80339887498949 x2 = -161.80339887498948",
  "args: (0, 7, 4)": "result: x=-0.5714285714285714",
  "args: (7, 1, -5)": "result: d = 141 x1 = -45.06019730463271 x2 = 38.06019730463271",
  "args: (-4, 2, 8)": "result: d = 132 x1 = 26.978250586152114 x2 = -18.978250586152114",
  "args: (-5, -3, -7)": "result: d = -131 нет действительных корней",
  "args: (0, 10, 9)": "result: x=-0.9",
  "args: (-6, -2, 3)": "result: d = 76 x1 = 20.153393661244046 x2 = -32.153393661244046",
  "args: (-2, -1, 10)": "result: d = 81 x1 = 8.0 x2 = -10.0",
  "args: (6, -3, -2)": "result: d = 57 x1 = -13.64950330581225 x2 = 31.64950330581225",
  "args: (3, 4, -2)": "result: d = 40 x1 = -15.48683298050514 x2 = 3.4868329805051386",
  "args: (7, 10, 4)": "result: d = -12 нет действительных корней",
  "args: (-5, -2, 1)": "result: d = 24 x1 = 7.247448713915889 x2 = -17.24744871391589",
  "args: (5, -5, -3)": "result: d = 85 x1 = -10.548861143232218 x2 = 35.548861143232216",
  "args: (-8, -8, -9)": "result: d = -224 нет действительных корней",
  "args: (3, -10, -3)": "result: d = 136 x1 = -2.4928556845359022 x2 = 32.492855684535904",
  "args: (0, 7, -9)": "result: x=1.2857142857142858",
  "args: (9, -9, 4)": "result: d = -63 нет действительных корней",
  "args: (3, 3, 3)": "result: d = -27 нет действительных корней",
  "args: (5, 10, -10)": "result: d = 300 x1 = -68.30127018922194 x2 = 18.30127018922194",
  "args: (9, -10, -3)": "result: d = 208 x1 = -19.899922958351805 x2 = 109.89992295835181",
  "args: (7, -9, 3)": "result: d = -3 нет действительных корней",
  "args: (-8, 6, 9)": "result: d = 324 x1 = 96.0 x2 = -48.0",
  "args: (8, -2, -8)": "result: d = 260 x1 = -56.49806198638839 x2 = 72.4980619863884",
  "args: (-6, -1, -8)": "result: d = -191 нет действительных корней",
  "args: (3, 6, 0)": "result: d = 36 x1 = -18.0 x2 = -0.0",
  "args: (5, -9, 2)": "result: d = 41 x1 = 6.492189406417879 x2 = 38.50781059358212",
  "args: (6, 3, -6)": "result: d = 153 x1 = -46.107950630558946 x2 = 28.107950630558943",
  "args: (0, -2, 2)": "result: x=1.0",
  "args: (5, 10, 0)": "result: d = 100 x1 = -50.0 x2 = -0.0",
  "args: (-2, -8, 3)": "result: d = 88 x1 = 1.3808315196468595 x2 = -17.38083151964686",
  "args: (4, 7, 8)": "result: d = -79 нет действительных корней",
  "args: (10, 10, -1)": "result: d = 140 x1 = -109.16079783099616 x2 = 9.160797830996161",
  "args: (10, 7, 2)": "result: d = -31 нет действительных корней",
  "args: (-3, -2, -9)": "result: d = -104 нет действительных корней",
  "args: (-8, -10, -1)": "result: d = 68 x1 = -7.015154995058715 x2 = -72.98484500494129",
  "args: (-4, -1, 3)": "result: d = 49 x1 = 12.0 x2 = -16.0",
  "args: (-8, 2, -10)": "result: d = -316 нет действительных корней",
  "args: (10, 5, -6)": "result: d = 265 x1 = -106.39410298049853 x2 = 56.39410298049853",
  "args: (-6, 3, -7)": "result: d = -159 нет действительных корней",
  "args: (2, -10, -10)": "result: d = 180 x1 = -3.416407864998739 x2 = 23.41640786499874",
  "args: (-5, -6, 0)": "result: d = 36 x1 = 0.0 x2 = -30.0",
  "args: (-7, -6, -4)": "result: d = -76 нет действительных корней",
  "args: (4, 1, -10)": "result: d = 161 x1 = -27.37715508089904 x2 = 23.37715508089904",
  "args: (3, 2, 2)": "result: d = -20 нет действительных корней",
  "args: (-8, 6, -9)": "result: d = -252 нет действительных корней",
  "args: (-9, 5, -4)": "result: d = -119 нет действительных корней",
  "args: (-7, 4, 9)": "result: d = 268 x1 = 71.29746940310716 x2 = -43.29746940310715",
  "args: (1, -5, 1)": "result: d = 21 x1 = 0.20871215252208009 x2 = 4.7912878474779195",
  "args: (-8, -3, -5)": "result: d = -151 нет действительных корней",
  "args: (9, 2, 1)": "result: d = -32 нет действительных корней",
  "args: (-5, 3, 4)": "result: d = 89 x1 = 31.084952830141507 x2 = -16.084952830141507",
  "args: (10, 2, 7)": "result: d = -276 нет действительных корней"
}